knight/__init__.py
knight/knight.py
knight-1.1.2.dist-info/METADATA
knight-1.1.2.dist-info/WHEEL
knight-1.1.2.dist-info/entry_points.txt
knight-1.1.2.dist-info/top_level.txt
knight-1.1.2.dist-info/RECORD
