Metadata-Version: 2.1
Name: knight
Version: 1.1.2
Summary: CLI version of Codechef for dummies...
Home-page: https://github.com/bradley101/knight
Author: Shantanu Banerjee
Author-email: hi@shantanubanerjee.com
License: MIT
Keywords: codechef competetive-programming coding cli
Platform: UNKNOWN
Requires-Python: >=3
Requires-Dist: mechanicalsoup
Requires-Dist: tabulate
